divergence/__init__.py
divergence/base.py
divergence/continuous.py
divergence/discrete.py
divergence/tests/__init__.py
divergence/tests/test_continuous.py
divergence/tests/test_discrete.py
divergence/tests/test_intersection.py
divergence-0.4.2.dist-info/LICENSE
divergence-0.4.2.dist-info/METADATA
divergence-0.4.2.dist-info/WHEEL
divergence-0.4.2.dist-info/top_level.txt
divergence-0.4.2.dist-info/RECORD
