Metadata-Version: 2.1
Name: divergence
Version: 0.4.2
Summary: Information Theoretic Measures of Entropy and Divergence
Home-page: https://github.com/michaelnowotny/divergence
Author: Michael Christoph Nowotny
Author-email: nowotnym@gmail.com
License: MIT
Platform: UNKNOWN
Classifier: License :: OSI Approved :: MIT License
Classifier: Programming Language :: Python
Classifier: Programming Language :: Python :: 3
Classifier: Programming Language :: Python :: 3.6
Classifier: Programming Language :: Python :: 3.7
Classifier: Programming Language :: Python :: 3.8
Classifier: Programming Language :: Python :: Implementation :: CPython
Requires-Python: >=3.6.0
Requires-Dist: cocos
Requires-Dist: cubature
Requires-Dist: numba
Requires-Dist: numpy
Requires-Dist: pytest
Requires-Dist: scipy
Requires-Dist: statsmodels
